MANIFEST.in
account_tax.xml
account_tax_code.xml
l10n_pa_chart.xml
l10n_pa_wizard.xml
setup.py
./__init__.py
./__openerp__.py
openerp_l10n_pa.egg-info/PKG-INFO
openerp_l10n_pa.egg-info/SOURCES.txt
openerp_l10n_pa.egg-info/dependency_links.txt
openerp_l10n_pa.egg-info/requires.txt
openerp_l10n_pa.egg-info/top_level.txt
static/src/img/icon.png